__init__.py
__main__.py
cli.py
client.py
collection.py
config.py
disbursement.py
errors.py
remittance.py
utils.py
lite_mtnmomo-0.0.3.dist-info/METADATA
lite_mtnmomo-0.0.3.dist-info/WHEEL
lite_mtnmomo-0.0.3.dist-info/entry_points.txt
lite_mtnmomo-0.0.3.dist-info/top_level.txt
lite_mtnmomo-0.0.3.dist-info/RECORD
