Metadata-Version: 2.1
Name: lite-mtnmomo
Version: 0.0.3
Summary: A lite Python wrapper for the MTN MoMo API.
Home-page: https://github.com/sikaili99/lite-python-mtnmomo-api
Author: sikaili99
Author-email: sikaili99@gmail.com
License: MIT license
Keywords: MoMo API,MoMo API Python Wrapper,MoMo API Python,MTN Zambia MoMO API Python
Platform: UNKNOWN
Classifier: Development Status :: 5 - Production/Stable
Classifier: Intended Audience :: Developers
Classifier: License :: OSI Approved :: MIT License
Classifier: Operating System :: Unix
Classifier: Operating System :: POSIX
Classifier: Operating System :: Microsoft :: Windows
Classifier: Programming Language :: Python
Classifier: Programming Language :: Python :: 2.7
Classifier: Programming Language :: Python :: 3
Classifier: Programming Language :: Python :: 3.4
Classifier: Programming Language :: Python :: 3.5
Classifier: Programming Language :: Python :: 3.6
Classifier: Programming Language :: Python :: 3.7
Classifier: Programming Language :: Python :: Implementation :: CPython
Classifier: Programming Language :: Python :: Implementation :: PyPy
Classifier: Topic :: Utilities
Requires-Dist: click
Requires-Dist: phonenumbers
Requires-Dist: requests
Provides-Extra: dev
Requires-Dist: semver ; extra == 'dev'
Provides-Extra: test
Requires-Dist: mock ; extra == 'test'
Requires-Dist: pytest ; extra == 'test'
Requires-Dist: pytest-bdd ; extra == 'test'
Requires-Dist: pytest-cov ; extra == 'test'
Requires-Dist: pytest-instafail ; extra == 'test'
Requires-Dist: pytest-pep8 ; extra == 'test'
Requires-Dist: pytest-sugar ; extra == 'test'
Requires-Dist: pytest-watch ; extra == 'test'
Requires-Dist: tox ; extra == 'test'
